{
  "parent": "minecraft:recipes/root",
  "criteria": {
    "has_glock_17_completed_schematic": {
      "conditions": {
        "items": [
          {
            "items": [
              "createarmsrace:glock_17_completed_schematic"
            ]
          }
        ]
      },
      "trigger": "minecraft:inventory_changed"
    },
    "has_the_recipe": {
      "conditions": {
        "recipe": "createarmsrace:glock_17_completed_schematic_copying"
      },
      "trigger": "minecraft:recipe_unlocked"
    }
  },
  "requirements": [
    [
      "has_glock_17_completed_schematic",
      "has_the_recipe"
    ]
  ],
  "rewards": {
    "recipes": [
      "createarmsrace:glock_17_completed_schematic_copying"
    ]
  },
  "sends_telemetry_event": false
}